{
  "kind": "collectionType",
  "collectionName": "projects",
  "info": {
    "singularName": "project",
    "pluralName": "projects",
    "displayName": "Projects",
    "description": ""
  },
  "options": {
    "draftAndPublish": true
  },
  "attributes": {
    "Title": {
      "type": "string"
    },
    "Thumbnail": {
      "type": "media",
      "multiple": false,
      "required": false,
      "allowedTypes": [
        "images",
        "files",
        "videos",
        "audios"
      ]
    },
    "Media": {
      "type": "media",
      "multiple": true,
      "required": false,
      "allowedTypes": [
        "images",
        "files",
        "videos",
        "audios"
      ]
    },
    "Description": {
      "type": "blocks"
    },
    "Type": {
      "type": "enumeration",
      "enum": [
        "Interactive",
        "Static",
        "Fashion",
        "Engineering",
        "Computer Music"
      ]
    }
  }
}
